mworks/__init__.py
src/__init__.py
mworks-2.0.0.dist-info/METADATA
mworks-2.0.0.dist-info/WHEEL
mworks-2.0.0.dist-info/top_level.txt
mworks-2.0.0.dist-info/RECORD
