Metadata-Version: 2.1
Name: mworks
Version: 2.0.0
Summary: A common utility framework for web microservices
Home-page: UNKNOWN
Author: msm
Author-email: msm@cert.pl
License: UNKNOWN
Platform: UNKNOWN
Classifier: Programming Language :: Python :: 3
Classifier: License :: OSI Approved :: MIT License
Classifier: Operating System :: OS Independent
Requires-Dist: flask
Requires-Dist: mistune
Requires-Dist: prometheus-flask-exporter
